[
    {
        "model":"redeem.voucher",
        "pk":1,
        "fields":{
            "jenis_voucher":"voucher belanja",
            "title_voucher" : "Voucher Belanja Rp25rb",
            "product_voucher" : "Indomaret",            
            "harga_poin":24000,
            "deskripsi": "Voucher belanja Indomaret senilai 25.000. Voucher berlaku hingga 31 Desember 2022"
        }
    },
    {
        "model":"redeem.voucher",
        "pk":2,
        "fields":{
            "jenis_voucher":"voucher belanja",
            "title_voucher" : "Voucher Belanja Rp50rb",
            "product_voucher" : "Indomaret",
            "harga_poin":49000,
            "deskripsi": "Voucher belanja Indomaret senilai 55.000. Voucher berlaku hingga 31 Desember 2022"
        }
    },
    {
        "model":"redeem.voucher",
        "pk":3,
        "fields":{
            "jenis_voucher":"voucher belanja",
            "title_voucher" : "Voucher Belanja Rp100rb",
            "product_voucher" : "Indomaret",
            "harga_poin":99000,
            "deskripsi": "Voucher belanja Indomaret senilai 100.000. Voucher berlaku hingga 31 Desember 2022"
        }
    },
    {
        "model":"redeem.voucher",
        "pk":4,
        "fields":{
            "jenis_voucher":"voucher belanja",
            "title_voucher" : "Voucher Belanja Rp25rb",
            "product_voucher" : "Alfamart",
            "harga_poin":24000,
            "deskripsi": "Voucher belanja Alfamart senilai 25.000. Voucher berlaku hingga 31 Desember 2022"
        }
    },
    {
        "model":"redeem.voucher",
        "pk":5,
        "fields":{
            "jenis_voucher":"voucher belanja",
            "title_voucher" : "Voucher Belanja Rp50rb",
            "product_voucher" : "Alfamart",
            "harga_poin":49000,
            "deskripsi": "Voucher belanja Alfamart senilai 50.000. Voucher berlaku hingga 31 Desember 2022"
        }
    },
    {
        "model":"redeem.voucher",
        "pk":6,
        "fields":{
            "jenis_voucher":"voucher belanja",
            "title_voucher" : "Voucher Belanja Rp100rb",
            "product_voucher" : "Alfamart",
            "harga_poin":99000,
            "deskripsi": "Voucher belanja Alfamart senilai 10.000. Voucher berlaku hingga 31 Desember 2022"
        }
    },
    {
        "model":"redeem.voucher",
        "pk":7,
        "fields":{
            "jenis_voucher":"pulsa",
            "title_voucher" : "Pulsa Telkomsel Rp10rb",
            "product_voucher" : "Telkomsel",
            "harga_poin":9000,
            "deskripsi": "Voucher pulsa telkomsel senilai 10.000. Voucher akan berupa nomor pulsa Prabayar dan hanya akan berlaku hingga 31 Desember 2022"
        }
    },
    
    {
        "model":"redeem.voucher",
        "pk":8,
        "fields":{
            "jenis_voucher":"pulsa",
            "title_voucher" : "Pulsa Telkomsel Rp25rb",
            "product_voucher" : "Telkomsel",
            "harga_poin":24000,
            "deskripsi": "Voucher pulsa telkomsel senilai 25.000. Voucher akan berupa nomor pulsa Prabayar dan hanya akan berlaku hingga 31 Desember 2022"
        }
    },
    {
        "model":"redeem.voucher",
        "pk":9,
        "fields":{
            "jenis_voucher":"pulsa",
            "title_voucher" : "Pulsa Telkomsel Rp50rb",
            "product_voucher" : "Telkomsel",
            "harga_poin":49000,
            "deskripsi": "Voucher pulsa telkomsel senilai 50.000. Voucher akan berupa nomor pulsa Prabayar dan hanya akan berlaku hingga 31 Desember 2022"
        }
    },
    {
        "model":"redeem.voucher",
        "pk":10,
        "fields":{
            "jenis_voucher":"pulsa",
            "title_voucher" : "Pulsa XL Rp10rb",
            "product_voucher" : "XL",
            "harga_poin":9000,
            "deskripsi": "Voucher pulsa XL senilai 10.000. Voucher akan berupa nomor pulsa Prabayar dan hanya akan berlaku hingga 31 Desember 2022"
        }
    },
    {
        "model":"redeem.voucher",
        "pk":11,
        "fields":{
            "jenis_voucher":"pulsa",
            "title_voucher" : "Pulsa XL Rp25rb",
            "product_voucher" : "XL",
            "harga_poin":24000,
            "deskripsi": "Voucher pulsa XL senilai 25.000. Voucher akan berupa nomor pulsa Prabayar dan hanya akan berlaku hingga 31 Desember 2022"
        }
    },
    {
        "model":"redeem.voucher",
        "pk":12,
        "fields":{
            "jenis_voucher":"pulsa",
            "title_voucher" : "Pulsa XL Rp50rb",
            "product_voucher" : "XL",
            "harga_poin":49000,
            "deskripsi": "Voucher pulsa XL senilai 50.000. Voucher akan berupa nomor pulsa Prabayar dan hanya akan berlaku hingga 31 Desember 2022"
        }
    },
    {
        "model":"redeem.voucher",
        "pk":13,
        "fields":{
            "jenis_voucher":"pulsa",
            "title_voucher" : "Pulsa Indosat Rp10rb",
            "product_voucher" : "Indosat",
            "harga_poin":9000,
            "deskripsi": "Voucher pulsa Indosat senilai 10.000. Voucher akan berupa nomor pulsa Prabayar dan hanya akan berlaku hingga 31 Desember 2022"
        }
    },
    {
        "model":"redeem.voucher",
        "pk":14,
        "fields":{
            "jenis_voucher":"pulsa",
            "title_voucher" : "Pulsa Indosat Rp25rb",
            "product_voucher" : "Indosat",
            "harga_poin":24000,
            "deskripsi": "Voucher pulsa Indosat senilai 25.000. Voucher akan berupa nomor pulsa Prabayar dan hanya akan berlaku hingga 31 Desember 2022"
        }
    },
    {
        "model":"redeem.voucher",
        "pk":15,
        "fields":{
            "jenis_voucher":"pulsa",
            "title_voucher" : "Pulsa Indosat Rp50rb",
            "product_voucher" : "Indosat",
            "harga_poin":49000,
            "deskripsi": "Voucher pulsa Indosat senilai 50.000. Voucher akan berupa nomor pulsa Prabayar dan hanya akan berlaku hingga 31 Desember 2022"
        }
    },

    {
        "model":"redeem.voucher",
        "pk":16,
        "fields":{
            "jenis_voucher":"voucher merchant",
            "title_voucher" : "Potongan Rp20rb Mcd",
            "product_voucher" : "Mcd",
            "harga_poin":19000,
            "deskripsi":  "Potongan senilai 20.000 di Mcd. Voucher hanya akan berlaku hingga 31 Desember 2022"
        }
    },
    {
        "model":"redeem.voucher",
        "pk":17,
        "fields":{
            "jenis_voucher":"voucher merchant",
            "title_voucher" : "Potongan Rp20rb Chatime",
            "product_voucher" : "Chatime",
            "harga_poin":19000,
            "deskripsi": "Potongan senilai 20.000 di Chatime. Voucher hanya akan berlaku hingga 31 Desember 2022"
        }
    },
    {
        "model":"redeem.voucher",
        "pk":18,
        "fields":{
            "jenis_voucher":"voucher merchant",
            "title_voucher" : "Potongan Rp20rb PizzaHut",
            "product_voucher" : "PizzaHut",
            "harga_poin":19000,
            "deskripsi": "Potongan senilai 20.000 di PizzaHut. Voucher hanya akan berlaku hingga 31 Desember 2022"
        }
    },
    {
        "model":"redeem.voucher",
        "pk":19,
        "fields":{
            "jenis_voucher":"voucher merchant",
            "title_voucher" : "Potongan Rp25rb Ruparupa.com",
            "product_voucher" : "Ruparupa.com",
            "harga_poin":24000,
            "deskripsi": "Potongan senilai 20.000 di Ruparupa.com. Voucher hanya akan berlaku hingga 31 Desember 2022"
        }
    },
    {
        "model":"redeem.voucher",
        "pk":20,
        "fields":{
            "jenis_voucher":"voucher merchant",
            "title_voucher" : "Potongan Rp25rb Ace Hardware",
            "product_voucher" : "Ace Hardware",
            "harga_poin":24000,
            "deskripsi": "Potongan senilai 20.000 di Ace Hardware. Voucher hanya akan berlaku hingga 31 Desember 2022"
        }
    },
    {
        "model":"redeem.voucher",
        "pk":21,
        "fields":{
            "jenis_voucher":"voucher merchant",
            "title_voucher" : "Pulsa Rp25rb IKEA",
            "product_voucher" : "IKEA",
            "harga_poin":24000,
            "deskripsi": "Potongan senilai 20.000 di IKEA. Voucher hanya akan berlaku hingga 31 Desember 2022"
        }
    }


   
]